plit/__init__.py
plit/_version.py
plit/core.py
plit/templates.py
plit/config/default.mplstyle
plit/config/general.json
plitlib-0.1.9.dist-info/LICENSE
plitlib-0.1.9.dist-info/METADATA
plitlib-0.1.9.dist-info/NOTICE
plitlib-0.1.9.dist-info/WHEEL
plitlib-0.1.9.dist-info/top_level.txt
plitlib-0.1.9.dist-info/RECORD
