Metadata-Version: 2.1
Name: plitlib
Version: 0.1.9
Summary: A wrapper for automating common matplotlib tasks
Home-page: https://github.com/awslabs/plit
Author: Josiah Davis
License: Apache 2.0
Keywords: plit visualization data science analytics analysis matplotlib
Platform: UNKNOWN
Classifier: Development Status :: 3 - Alpha
Classifier: Environment :: Console
Classifier: Intended Audience :: Developers
Classifier: Intended Audience :: Science/Research
Classifier: License :: OSI Approved :: MIT License
Classifier: Natural Language :: English
Classifier: Programming Language :: Python :: 3 :: Only
Classifier: Topic :: Scientific/Engineering :: Artificial Intelligence
Classifier: Topic :: Software Development :: Libraries :: Python Modules
Requires-Python: >=3.6.0
Requires-Dist: matplotlib
